<xml version="1.0">
<dashboard>
	<widget field="Left Value" type="Number" class="edu.wpi.first.smartdashboard.gui.elements.TextBox">
		<location x="831" y="257"/>
	</widget>
	<widget field="Right Value" type="Number" class="edu.wpi.first.smartdashboard.gui.elements.TextBox">
		<location x="991" y="266"/>
	</widget>
	<widget field="Basin Has Been Homed?" type="Boolean" class="edu.wpi.first.smartdashboard.gui.elements.TextBox">
		<location x="764" y="61"/>
	</widget>
	<widget field="Basin IsHoming?" type="Boolean" class="edu.wpi.first.smartdashboard.gui.elements.TextBox">
		<location x="760" y="108"/>
	</widget>
	<widget field="isCompromised?" type="Boolean" class="edu.wpi.first.smartdashboard.gui.elements.TextBox">
		<location x="756" y="154"/>
	</widget>
	<widget field="Auton selected" type="String" class="edu.wpi.first.smartdashboard.gui.elements.TextBox">
		<location x="750" y="201"/>
	</widget>
	<widget field="Distance to Target Using Horizontal FOV" type="Number" class="edu.wpi.first.smartdashboard.gui.elements.TextBox">
		<location x="792" y="221"/>
	</widget>
	<widget field="Left Enc Value" type="Number" class="edu.wpi.first.smartdashboard.gui.elements.TextBox">
		<location x="778" y="180"/>
	</widget>
	<widget field="Gyro Value" type="Number" class="edu.wpi.first.smartdashboard.gui.elements.TextBox">
		<location x="762" y="41"/>
	</widget>
	<widget field="Basin IsMoving?" type="Boolean" class="edu.wpi.first.smartdashboard.gui.elements.TextBox">
		<location x="752" y="132"/>
	</widget>
	<widget field="Distance to Target" type="Number" class="edu.wpi.first.smartdashboard.gui.elements.TextBox">
		<location x="765" y="78"/>
	</widget>
	<widget field="Right Enc Value" type="Number" class="edu.wpi.first.smartdashboard.gui.elements.TextBox">
		<location x="953" y="184"/>
	</widget>
	<widget field="Angle to Target" type="Number" class="edu.wpi.first.smartdashboard.gui.elements.TextBox">
		<location x="544" y="48"/>
	</widget>
	<widget field="Gear Good?" type="Boolean" class="edu.wpi.first.smartdashboard.gui.elements.TextBox">
		<location x="788" y="288"/>
	</widget>
	<widget field="Basin Position" type="Number" class="edu.wpi.first.smartdashboard.gui.elements.TextBox">
		<location x="534" y="14"/>
	</widget>
	<widget field="Basin Limit Switch" type="Boolean" class="edu.wpi.first.smartdashboard.gui.elements.TextBox">
		<location x="521" y="69"/>
		<height>20</height>
	</widget>
	<widget field="Auto Selector" type="String" class="edu.wpi.first.smartdashboard.gui.elements.TextBox">
		<location x="512" y="115"/>
	</widget>
	<widget field="Basin Enc Position" type="Number" class="edu.wpi.first.smartdashboard.gui.elements.TextBox">
		<location x="515" y="92"/>
	</widget>
	<widget field="Basin Target" type="Number" class="edu.wpi.first.smartdashboard.gui.elements.TextBox">
		<location x="510" y="137"/>
	</widget>
	<widget field="isMoving?" type="Boolean" class="edu.wpi.first.smartdashboard.gui.elements.TextBox">
		<location x="518" y="319"/>
	</widget>
	<widget field="Alliterative Autoniomous Appointment" type="String Chooser" class="edu.wpi.first.smartdashboard.gui.elements.Chooser">
		<location x="478" y="165"/>
	</widget>
	<widget field="isTurning?" type="Boolean" class="edu.wpi.first.smartdashboard.gui.elements.TextBox">
		<location x="553" y="367"/>
	</widget>
</dashboard>
<live-window>
</live-window>
</xml>